azuresdkoplib/__init__.py
azuresdkoplib/op_autoscale_settings.py
azuresdkoplib/op_func.py
azuresdkoplib/op_image.py
azuresdkoplib/op_keyvault.py
azuresdkoplib/op_load_balance.py
azuresdkoplib/op_nic.py
azuresdkoplib/op_nsg.py
azuresdkoplib/op_public_ip.py
azuresdkoplib/op_resource_group.py
azuresdkoplib/op_scale_set.py
azuresdkoplib/op_service_bus_queue.py
azuresdkoplib/op_ss_vm.py
azuresdkoplib/op_status_code.py
azuresdkoplib/op_storage.py
azuresdkoplib/op_subnet.py
azuresdkoplib/op_virtual_network.py
azuresdkoplib/op_vm.py
azuresdkoplib-1.1.dist-info/METADATA
azuresdkoplib-1.1.dist-info/RECORD
azuresdkoplib-1.1.dist-info/WHEEL
azuresdkoplib-1.1.dist-info/top_level.txt
